f3_data_models/__init__.py
f3_data_models/models.py
f3_data_models/testing.py
f3_data_models/utils.py
f3_data_models-0.8.1.dist-info/METADATA
f3_data_models-0.8.1.dist-info/WHEEL
f3_data_models-0.8.1.dist-info/RECORD
