Metadata-Version: 2.4
Name: f3-data-models
Version: 0.8.1
Summary: The data schema and models for F3 Nation applications.
License: MIT
Author: Evan Petzoldt
Author-email: evan.petzoldt@protonmail.com
Requires-Python: >=3.12,<4.0
Classifier: License :: OSI Approved :: MIT License
Classifier: Programming Language :: Python :: 3
Classifier: Programming Language :: Python :: 3.12
Classifier: Programming Language :: Python :: 3.13
Classifier: Programming Language :: Python :: 3.14
Requires-Dist: alembic-postgresql-enum (>=1.6.1,<2.0.0)
Requires-Dist: psycopg2-binary (>=2.9.10,<3.0.0)
Requires-Dist: sqlalchemy (>=2.0.36,<3.0.0)
Requires-Dist: sqlalchemy-citext (>=1.8.0,<2.0.0)
Requires-Dist: sqlmodel (>=0.0.22,<0.0.23)
Project-URL: Documentation, https://github.io/F3-Nation/f3-data-models
Project-URL: Repository, https://github.com/F3-Nation/f3-data-models
